samgis_core/__init__.py
samgis_core/__version__.py
samgis_core/prediction_api/__init__.py
samgis_core/prediction_api/sam_onnx2.py
samgis_core/prediction_api/sam_onnx_inference.py
samgis_core/utilities/__init__.py
samgis_core/utilities/constants.py
samgis_core/utilities/create_folders_if_not_exists.py
samgis_core/utilities/frontend_builder.py
samgis_core/utilities/plot_images.py
samgis_core/utilities/serialize.py
samgis_core/utilities/session_logger.py
samgis_core/utilities/type_hints.py
samgis_core/utilities/utilities.py
samgis_core-3.4.2.dist-info/LICENSE
samgis_core-3.4.2.dist-info/METADATA
samgis_core-3.4.2.dist-info/WHEEL
samgis_core-3.4.2.dist-info/RECORD
