Metadata-Version: 2.3
Name: samgis_core
Version: 3.4.2
Summary: SamGIS CORE
License: MIT
Author: alessandro trinca tornidor
Author-email: alessandro@trinca.tornidor.com
Requires-Python: >=3.10, <3.13
Classifier: License :: OSI Approved :: MIT License
Classifier: Programming Language :: Python :: 3
Classifier: Programming Language :: Python :: 3.10
Classifier: Programming Language :: Python :: 3.11
Classifier: Programming Language :: Python :: 3.12
Requires-Dist: bson (>=0.5.10,<0.6.0)
Requires-Dist: numpy (>=2.2.4,<3.0.0)
Requires-Dist: pillow (>=11.1.0,<12.0.0)
Requires-Dist: python-dotenv (>=1.0.1,<2.0.0)
Requires-Dist: structlog (>=25.2.0,<26.0.0)
Project-URL: Source, https://gitlab.com/aletrn/samgis_core
